junjo/__init__.py
junjo/app.py
junjo/condition.py
junjo/edge.py
junjo/graph.py
junjo/node.py
junjo/run_concurrent.py
junjo/state.py
junjo/store.py
junjo/util.py
junjo/workflow.py
junjo/graphviz/__init__.py
junjo/graphviz/utils.py
junjo/react_flow/schemas.py
junjo/telemetry/__init__.py
junjo/telemetry/hook_manager.py
junjo/telemetry/hook_schema.py
junjo/telemetry/junjo_server_otel_exporter.py
junjo/telemetry/otel_schema.py
junjo/telemetry/junjo_server/__init__.py
junjo/telemetry/junjo_server/client.py
junjo/telemetry/junjo_server/proto/__init__.py
junjo/telemetry/junjo_server/proto_gen/node_log_pb2.py
junjo/telemetry/junjo_server/proto_gen/node_log_pb2.pyi
junjo/telemetry/junjo_server/proto_gen/node_log_pb2_grpc.py
junjo/telemetry/junjo_server/proto_gen/workflow_log_pb2.py
junjo/telemetry/junjo_server/proto_gen/workflow_log_pb2.pyi
junjo/telemetry/junjo_server/proto_gen/workflow_log_pb2_grpc.py
junjo/telemetry/junjo_server/proto_gen/workflow_metadata_pb2.py
junjo/telemetry/junjo_server/proto_gen/workflow_metadata_pb2.pyi
junjo/telemetry/junjo_server/proto_gen/workflow_metadata_pb2_grpc.py
junjo-0.61.1.dist-info/licenses/LICENSE
junjo-0.61.1.dist-info/METADATA
junjo-0.61.1.dist-info/WHEEL
junjo-0.61.1.dist-info/top_level.txt
junjo-0.61.1.dist-info/RECORD
