Metadata-Version: 2.4
Name: junjo
Version: 0.61.1
Summary: AI graph workflow and state machine framework for building debuggable AI Agents.
Author-email: Matthew Rideout <boon4376@gmail.com>
License: 
Project-URL: Docs, https://python-api.junjo.ai/
Project-URL: Repository, https://github.com/mdrideout/junjo
Project-URL: Bug Tracker, https://github.com/mdrideout/junjo/issues
Project-URL: Telemetry Server, https://github.com/mdrideout/junjo-server
Classifier: Programming Language :: Python :: 3
Classifier: Programming Language :: Python :: 3.11
Classifier: Operating System :: OS Independent
Classifier: Intended Audience :: Developers
Classifier: Topic :: Scientific/Engineering :: Artificial Intelligence
Classifier: Topic :: Software Development :: Libraries :: Application Frameworks
Classifier: Topic :: Software Development :: Libraries :: Python Modules
Classifier: Development Status :: 5 - Production/Stable
Classifier: License :: OSI Approved :: Apache Software License
Requires-Python: >=3.11
License-File: LICENSE
Requires-Dist: grpcio>=1.75.1
Requires-Dist: jsonpatch>=1.33
Requires-Dist: nanoid>=2.0.0
Requires-Dist: opentelemetry-exporter-otlp-proto-grpc>=1.37.0
Requires-Dist: opentelemetry-sdk>=1.37.0
Requires-Dist: pydantic>=2.10.6
Provides-Extra: dev
Requires-Dist: sphinx; extra == "dev"
Requires-Dist: furo; extra == "dev"
Requires-Dist: pytest; extra == "dev"
Requires-Dist: pytest-asyncio; extra == "dev"
Requires-Dist: ruff~=0.9.5; extra == "dev"
Requires-Dist: sphinx-rtd-theme; extra == "dev"
Requires-Dist: simple-sphinx-xml-sitemap; extra == "dev"
Requires-Dist: mypy; extra == "dev"
Requires-Dist: grpcio-tools; extra == "dev"
Requires-Dist: build>=1.2.1; extra == "dev"
Requires-Dist: twine>=6.1.0; extra == "dev"
Requires-Dist: pre-commit; extra == "dev"
Provides-Extra: graphviz
Requires-Dist: graphviz; extra == "graphviz"
Dynamic: license-file
